random_word_gen/__init__.py
random_word_gen/main.py
random_word_gen-0.6.1.dist-info/METADATA
random_word_gen-0.6.1.dist-info/WHEEL
random_word_gen-0.6.1.dist-info/top_level.txt
random_word_gen-0.6.1.dist-info/RECORD
