Metadata-Version: 2.1
Name: random-word-gen
Version: 0.6.1
